{
  "timestamp": "2025-10-12T23:12:38.354102",
  "scenario_id": "20251012_231238_355",
  "graph_structure": {
    "num_nodes": 9,
    "num_edges": 72,
    "node_features_shape": [
      9,
      21
    ],
    "edge_features_shape": [
      72,
      6
    ]
  },
  "node_features": {
    "coordinates": [
      [
        0.9142857193946838,
        0.44117647409439087
      ],
      [
        0.9333333373069763,
        0.47058823704719543
      ],
      [
        0.8952381014823914,
        0.4117647111415863
      ],
      [
        0.8761904835700989,
        0.45588234066963196
      ],
      [
        0.9047619104385376,
        0.4264705777168274
      ],
      [
        0.9238095283508301,
        0.4852941036224365
      ],
      [
        0.8857142925262451,
        0.3970588147640228
      ],
      [
        0.9523809552192688,
        0.5
      ],
      [
        1.0,
        0.0
      ]
    ],
    "velocities": [
      [
        0.0,
        0.0
      ],
      [
        0.0,
        0.0
      ],
      [
        0.0,
        0.0
      ],
      [
        0.0,
        0.0
      ],
      [
        0.0,
        0.0
      ],
      [
        0.0,
        0.0
      ],
      [
        0.0,
        0.0
      ],
      [
        0.0,
        0.0
      ],
      [
        0.0,
        0.0
      ]
    ],
    "team_flags": {
      "attackers": [
        1.0,
        1.0,
        1.0,
        1.0,
        0.0,
        0.0,
        0.0,
        0.0,
        0.0
      ],
      "goalkeepers": [
        0.0,
        0.0,
        0.0,
        0.0,
        0.0,
        0.0,
        0.0,
        1.0,
        0.0
      ]
    },
    "distances": {
      "ball_distance": [
        0.2503751516342163,
        0.2618524134159088,
        0.24048112332820892,
        0.268717497587204,
        0.24521753191947937,
        0.27143844962120056,
        0.2361912578344345,
        0.27471455931663513,
        0.0
      ],
      "goal_distance": [
        0.07873041927814484,
        0.05819620192050934,
        0.1001628190279007,
        0.1066514328122139,
        0.0893741026520729,
        0.06444858759641647,
        0.11105429381132126,
        0.0399693138897419,
        0.0
      ]
    },
    "all_features": [
      [
        0.9142857193946838,
        0.44117647409439087,
        0.0,
        0.0,
        1.0,
        0.0,
        0.2503751516342163,
        0.07873041927814484,
        0.0,
        180.0,
        0.699999988079071,
        1.0,
        0.699999988079071,
        0.6000000238418579,
        0.6499999761581421,
        0.5,
        0.0,
        0.0,
        0.0,
        0.0,
        0.0
      ],
      [
        0.9333333373069763,
        0.47058823704719543,
        0.0,
        0.0,
        1.0,
        0.0,
        0.2618524134159088,
        0.05819620192050934,
        0.0,
        180.0,
        0.699999988079071,
        1.0,
        0.699999988079071,
        0.6000000238418579,
        0.6499999761581421,
        0.5,
        0.0,
        0.0,
        0.0,
        0.0,
        0.0
      ],
      [
        0.8952381014823914,
        0.4117647111415863,
        0.0,
        0.0,
        1.0,
        0.0,
        0.24048112332820892,
        0.1001628190279007,
        0.0,
        180.0,
        0.699999988079071,
        1.0,
        0.699999988079071,
        0.6000000238418579,
        0.6499999761581421,
        0.5,
        0.0,
        0.0,
        0.0,
        0.0,
        0.0
      ],
      [
        0.8761904835700989,
        0.45588234066963196,
        0.0,
        0.0,
        1.0,
        0.0,
        0.268717497587204,
        0.1066514328122139,
        0.0,
        180.0,
        0.699999988079071,
        1.0,
        0.699999988079071,
        0.6000000238418579,
        0.6499999761581421,
        0.5,
        0.0,
        0.0,
        0.0,
        0.0,
        0.0
      ],
      [
        0.9047619104385376,
        0.4264705777168274,
        0.0,
        0.0,
        0.0,
        0.0,
        0.24521753191947937,
        0.0893741026520729,
        0.0,
        180.0,
        0.699999988079071,
        0.0,
        0.699999988079071,
        0.6000000238418579,
        0.6499999761581421,
        0.5,
        0.0,
        0.0,
        0.0,
        0.0,
        0.0
      ],
      [
        0.9238095283508301,
        0.4852941036224365,
        0.0,
        0.0,
        0.0,
        0.0,
        0.27143844962120056,
        0.06444858759641647,
        0.0,
        180.0,
        0.699999988079071,
        0.0,
        0.699999988079071,
        0.6000000238418579,
        0.6499999761581421,
        0.5,
        0.0,
        0.0,
        0.0,
        0.0,
        0.0
      ],
      [
        0.8857142925262451,
        0.3970588147640228,
        0.0,
        0.0,
        0.0,
        0.0,
        0.2361912578344345,
        0.11105429381132126,
        0.0,
        180.0,
        0.699999988079071,
        0.0,
        0.699999988079071,
        0.6000000238418579,
        0.6499999761581421,
        0.5,
        0.0,
        0.0,
        0.0,
        0.0,
        0.0
      ],
      [
        0.9523809552192688,
        0.5,
        0.0,
        0.0,
        0.0,
        1.0,
        0.27471455931663513,
        0.0399693138897419,
        0.0,
        180.0,
        0.699999988079071,
        0.0,
        0.699999988079071,
        0.6000000238418579,
        0.6499999761581421,
        0.5,
        0.0,
        0.0,
        0.0,
        0.0,
        0.0
      ],
      [
        1.0,
        0.0,
        0.0,
        0.0,
        0.0,
        0.0,
        0.0,
        0.0,
        0.0,
        0.0,
        0.0,
        0.0,
        0.0,
        0.0,
        0.0,
        0.0,
        0.0,
        0.0,
        0.0,
        0.0,
        0.0
      ]
    ]
  },
  "player_input": {
    "total_players": 8,
    "attackers": [
      {
        "id": 21,
        "x": 96,
        "y": 30,
        "team": "attacker"
      },
      {
        "id": 22,
        "x": 98,
        "y": 32,
        "team": "attacker"
      },
      {
        "id": 23,
        "x": 94,
        "y": 28,
        "team": "attacker"
      },
      {
        "id": 24,
        "x": 92,
        "y": 31,
        "team": "attacker"
      }
    ],
    "defenders": [
      {
        "id": 25,
        "x": 95,
        "y": 29,
        "team": "defender"
      },
      {
        "id": 26,
        "x": 97,
        "y": 33,
        "team": "defender"
      },
      {
        "id": 27,
        "x": 93,
        "y": 27,
        "team": "defender"
      }
    ],
    "goalkeepers": [
      {
        "id": 28,
        "x": 100,
        "y": 34,
        "team": "keeper"
      }
    ]
  },
  "model_outputs": {
    "receiver_scores": {
      "23": 0.6079976558685303,
      "24": 0.6078127026557922,
      "22": 0.6077920198440552,
      "21": 0.6077601909637451
    },
    "shot_confidence": 0.49757546186447144,
    "primary_receiver": 23,
    "tactical_decision": "Layoff to create angle",
    "decision_reason": "Moderate confidence, setup play"
  },
  "formation_analysis": {
    "attacker_positions": [
      [
        96,
        30
      ],
      [
        98,
        32
      ],
      [
        94,
        28
      ],
      [
        92,
        31
      ]
    ],
    "defender_positions": [
      [
        95,
        29
      ],
      [
        97,
        33
      ],
      [
        93,
        27
      ]
    ],
    "formation_center_x": 95.625,
    "formation_width": 8
  }
}